{
    "auth": {
        "facebook": {
            "token_url": "https://graph.facebook.com/v2.10/oauth/access_token",
            "auth_url": "https://www.facebook.com/v2.10/dialog/oauth",
            "app_id": "YOUR_APP_ID",
            "app_secret": "YOUR_APP_SECRET",
            "callback": "YOUR_FACEBOOK_CALLBACK_URL"
        },
        "twitter": {
            "consumer_key": "YOUR_CONSUMER_KEY",
            "consumer_secret": "YOUR_CONSUMER_SECRET",
            "callback": "YOUR_TWITTER_CALLBACK_URL"
        },
        "jwt": {
            "secret": "A_CUSTOM_SECRET (say Hakunamatata)"
        }
    },
    "email": {
        "service": "EMAIL SERVICE",
        "username": "EMAIL ID",
        "password": "EMAIL PASSWORD"
    }
}